thonny_lahendus-9.2.0.dist-info/licenses/LICENSE
thonnycontrib/easy/__init__.py
thonnycontrib/easy/demo_exercise_provider.py
thonnycontrib/easy/easy_provider.py
thonnycontrib/easy/htmltext.py
thonnycontrib/easy/templates_generator.py
thonnycontrib/easy/ui.py
thonnycontrib/easy/res/broken.png
thonnycontrib/easy/templates/authenticate.mustache
thonnycontrib/easy/templates/exercise.mustache
thonnycontrib/easy/templates/update_en.mustache
thonnycontrib/easy/templates/update_et.mustache
thonny_lahendus-9.2.0.dist-info/METADATA
thonny_lahendus-9.2.0.dist-info/WHEEL
thonny_lahendus-9.2.0.dist-info/top_level.txt
thonny_lahendus-9.2.0.dist-info/RECORD
