Metadata-Version: 2.4
Name: thonny-lahendus
Version: 9.2.0
Summary: Thonny plugin for lahendus.ut.ee
Home-page: https://github.com/kspar/easy-thonny
Author: Priit Paluoja
Author-email: priit.paluoja@gmail.com
License-Expression: MIT
Classifier: Programming Language :: Python :: 3
Classifier: Operating System :: OS Independent
Requires-Python: >=3.7
License-File: LICENSE
Requires-Dist: easy-py>=0.7.2
Requires-Dist: thonny>=4.1.4
Requires-Dist: pillow>=11.3.0
Requires-Dist: chevron>=0.13.1
Requires-Dist: requests>=2.27.1
Dynamic: author
Dynamic: author-email
Dynamic: classifier
Dynamic: description
Dynamic: description-content-type
Dynamic: home-page
Dynamic: license
Dynamic: license-file
Dynamic: license-expression
Dynamic: requires-dist
Dynamic: requires-python
Dynamic: summary
